LICENSE
snyk_metrics/__init__.py
snyk_metrics/client.py
snyk_metrics/clients/__init__.py
snyk_metrics/clients/base.py
snyk_metrics/clients/dogstatsd.py
snyk_metrics/clients/prometheus.py
snyk_metrics/exceptions.py
snyk_metrics/metrics.py
snyk_metrics-0.0.6.dist-info/LICENSE
snyk_metrics-0.0.6.dist-info/WHEEL
snyk_metrics-0.0.6.dist-info/METADATA
snyk_metrics-0.0.6.dist-info/RECORD
