Metadata-Version: 2.1
Name: snyk-metrics
Version: 0.0.6
Summary: Python library to interact transparently with Prometheus, Pushgateway and Dogstatsd.
Home-page: https://github.com/snyk/python-metrics
License: Apache-2.0
Keywords: prometheus,datadog,metrics
Author: Snyk Security R&D
Author-email: security-engineering@snyk.io
Requires-Python: >=3.7,<4.0
Classifier: License :: OSI Approved :: Apache Software License
Classifier: Programming Language :: Python :: 3
Classifier: Programming Language :: Python :: 3.7
Classifier: Programming Language :: Python :: 3.8
Classifier: Programming Language :: Python :: 3.9
Classifier: Programming Language :: Python :: 3.10
Classifier: Programming Language :: Python :: 3.11
Requires-Dist: datadog (>=0.43.0,<1.0.0)
Requires-Dist: prometheus-client (>=0.12.0,<1.0.0)
Project-URL: Repository, https://github.com/snyk/python-metrics
